pion/__init__.py
pion/_version.py
pion/core.py
pion/antlr/IonTextLexer.py
pion/antlr/IonTextListener.py
pion/antlr/IonTextParser.py
pionic/__init__.py
pionic/_version.py
pionic/core.py
pionic/antlr/IonTextLexer.py
pionic/antlr/IonTextListener.py
pionic/antlr/IonTextParser.py
pionic-0.0.1.dist-info/DESCRIPTION.rst
pionic-0.0.1.dist-info/METADATA
pionic-0.0.1.dist-info/RECORD
pionic-0.0.1.dist-info/WHEEL
pionic-0.0.1.dist-info/metadata.json
pionic-0.0.1.dist-info/top_level.txt
