Metadata-Version: 2.0
Name: pionic
Version: 0.0.1
Summary: A Python 3 library for the Ion format.
Home-page: https://github.com/tlocke/pionic
Author: Tony Locke
Author-email: tlocke@tlocke.org.uk
License: UNKNOWN
Platform: UNKNOWN
Requires-Dist: antlr4-python3-runtime (==4.7)
Requires-Dist: arrow (==0.10.0)
